apie/__init__.py
apie/__main__.py
apie/apie.py
apie/api/__init__.py
apie/api/api_hack.py
apie/api/api_help.py
apie/api/api_multi.py
apie/auth/__init__.py
apie/auth/auth_from_config.py
apie/auth/auth_noauth.py
apie-0.0.8.dist-info/METADATA
apie-0.0.8.dist-info/WHEEL
apie-0.0.8.dist-info/entry_points.txt
apie-0.0.8.dist-info/top_level.txt
apie-0.0.8.dist-info/RECORD
