Metadata-Version: 2.2
Name: apie
Version: 0.0.8
Summary: Application Programming Interface of Eons
Home-page: https://github.com/eons-dev/apie.exe
Author: Eons
Author-email: support@eons.llc
Project-URL: Bug Tracker, https://github.com/eons-dev/apie.exe/issues
Classifier: Programming Language :: Python :: 3
Classifier: License :: OSI Approved :: GNU Affero General Public License v3
Classifier: Operating System :: OS Independent
Classifier: Development Status :: 3 - Alpha
Requires-Python: >=3.7
Requires-Dist: flask_socketio
Requires-Dist: eons
Requires-Dist: elderlang
Requires-Dist: jsonpickle
Requires-Dist: eventlet
Requires-Dist: flask
